CHANGES.txt
CONTRIBUTORS.txt
README.txt
bootstrap.py
buildout.cfg
setup.py
cs/__init__.py
cs.recipe.eggpath.egg-info/PKG-INFO
cs.recipe.eggpath.egg-info/SOURCES.txt
cs.recipe.eggpath.egg-info/dependency_links.txt
cs.recipe.eggpath.egg-info/entry_points.txt
cs.recipe.eggpath.egg-info/namespace_packages.txt
cs.recipe.eggpath.egg-info/not-zip-safe
cs.recipe.eggpath.egg-info/requires.txt
cs.recipe.eggpath.egg-info/top_level.txt
cs/recipe/__init__.py
cs/recipe/eggpath/__init__.py
cs/recipe/eggpath/tests/__init__.py
cs/recipe/eggpath/tests/test_docs.py