Metadata-Version: 1.1
Name: cs.recipe.eggpath
Version: 1.8
Summary: A simple recipe to get the path of an egg
Home-page: http://www.codesyntax.com/products
Author: Mikel Larreategi
Author-email: mlarreategi@codesyntax.com
License: ZPL
Platform: UNKNOWN
Classifier: Framework :: Buildout
Classifier: Intended Audience :: Developers
Classifier: Topic :: Software Development :: Build Tools
Classifier: Topic :: Software Development :: Libraries :: Python Modules
Classifier: License :: OSI Approved :: Zope Public License
